quantcli/cli.py
quantcli/core/__init__.py
quantcli/core/backtest.py
quantcli/core/data.py
quantcli/core/factor.py
quantcli/datasources/__init__.py
quantcli/datasources/akshare.py
quantcli/datasources/baostock.py
quantcli/datasources/base.py
quantcli/datasources/cache.py
quantcli/datasources/mixed.py
quantcli/datasources/mysql.py
quantcli/datasources/sync/__init__.py
quantcli/datasources/sync/akshare.py
quantcli/datasources/sync/base.py
quantcli/datasources/sync/gm.py
quantcli/factors/__init__.py
quantcli/factors/base.py
quantcli/factors/compute.py
quantcli/factors/loader.py
quantcli/factors/pipeline.py
quantcli/factors/ranking.py
quantcli/factors/screening.py
quantcli/parser/__init__.py
quantcli/parser/constants.py
quantcli/parser/formula.py
quantcli/utils/__init__.py
quantcli/utils/logger.py
quantcli/utils/path.py
quantcli/utils/time.py
quantcli/utils/validate.py
quantcli-0.1.2.dist-info/licenses/LICENSE
quantcli-0.1.2.dist-info/METADATA
quantcli-0.1.2.dist-info/WHEEL
quantcli-0.1.2.dist-info/entry_points.txt
quantcli-0.1.2.dist-info/top_level.txt
quantcli-0.1.2.dist-info/RECORD
