Metadata-Version: 2.4
Name: quantcli
Version: 0.1.2
Summary: 面向AI的多因子量化选股策略挖掘工具，AI Agent 友好 CLI
Author-email: QuantCLI Team <quantcli@example.com>
Project-URL: repository, https://github.com/wumu2013/quantcli
Classifier: Development Status :: 3 - Alpha
Classifier: Intended Audience :: Developers
Classifier: License :: OSI Approved :: MIT License
Classifier: Programming Language :: Python :: 3.9
Classifier: Programming Language :: Python :: 3.10
Classifier: Programming Language :: Python :: 3.11
Classifier: Programming Language :: Python :: 3.12
Requires-Python: >=3.9
License-File: LICENSE
Requires-Dist: click>=8.0
Requires-Dist: pandas>=2.0
Requires-Dist: numpy>=1.24
Requires-Dist: pyarrow>=12.0
Requires-Dist: backtrader>=1.9
Requires-Dist: tabulate>=0.9
Requires-Dist: pyyaml>=6.0
Requires-Dist: pymysql>=1.1
Provides-Extra: dev
Requires-Dist: pytest>=7.0; extra == "dev"
Requires-Dist: pytest-cov>=4.0; extra == "dev"
Dynamic: license-file
